num_to_str_repr/__init__.py
num_to_str_repr/constant.py
num_to_str_repr/number_converter.py
tests/__init__.py
tests/num_to_str_repr.py
num_to_str_repr-0.0.4.dist-info/LICENSE
num_to_str_repr-0.0.4.dist-info/METADATA
num_to_str_repr-0.0.4.dist-info/WHEEL
num_to_str_repr-0.0.4.dist-info/top_level.txt
num_to_str_repr-0.0.4.dist-info/RECORD
