Metadata-Version: 2.1
Name: num-to-str-repr
Version: 0.0.4
Summary: Simple package that converts numbers (int and float)
Home-page: https://github.com/IrinaLokhvytska/num_to_str_repr
Author: Iryna Lokhvytska
Author-email: ilokh@softserveinc.com
License: UNKNOWN
Platform: UNKNOWN
Classifier: Programming Language :: Python :: 3.6
Classifier: License :: OSI Approved :: MIT License
Classifier: Operating System :: OS Independent
License-File: LICENSE
